CHANGELOG.md
README.md
README.zh.md
rusty_req-0.4.25.dist-info/METADATA
rusty_req-0.4.25.dist-info/WHEEL
rusty_req.libs/libcrypto-bdaed0ea.so.1.1
rusty_req.libs/libssl-60250281.so.1.1
rusty_req.pyi
rusty_req/__init__.py
rusty_req/__init__.pyi
rusty_req/py.typed
rusty_req/rusty_req.cpython-313t-x86_64-linux-gnu.so
rusty_req-0.4.25.dist-info/RECORD
