Metadata-Version: 2.4
Name: rusty-req
Version: 0.4.25
Classifier: Programming Language :: Python
Classifier: Programming Language :: Python :: 3
Classifier: Programming Language :: Python :: 3 :: Only
Classifier: Programming Language :: Python :: 3.9
Classifier: Programming Language :: Python :: 3.10
Classifier: Programming Language :: Python :: 3.11
Classifier: Programming Language :: Python :: 3.12
Classifier: Programming Language :: Python :: 3.13
Classifier: Programming Language :: Rust
Classifier: Operating System :: Microsoft :: Windows
Classifier: Operating System :: POSIX :: Linux
Classifier: Operating System :: MacOS :: MacOS X
Classifier: Topic :: Internet :: WWW/HTTP
Classifier: Topic :: Software Development :: Libraries :: Python Modules
Classifier: Topic :: System :: Networking
Classifier: Framework :: AsyncIO
Classifier: Intended Audience :: Developers
Classifier: License :: OSI Approved :: MIT License
Summary: ⚡ High-performance async HTTP client in Rust with Python bindings for blazing-fast batch requests.
Author-email: KAY53N <kaysen820@gmail.com>
License: MIT
Requires-Python: >=3.9
Project-URL: Homepage, https://github.com/KAY53N/rusty-req
Project-URL: Repository, https://github.com/KAY53N/rusty-req
Project-URL: Bug Tracker, https://github.com/KAY53N/rusty-req/issues
Project-URL: Documentation, https://github.com/KAY53N/rusty-req#readme
Project-URL: Changelog, https://github.com/KAY53N/rusty-req/blob/main/CHANGELOG.md
